setup.py
rainbow/__init__.py
rainbow/cloudformation.py
rainbow/main.py
rainbow/templates.py
rainbow/yaml_loader.py
rainbow/datasources/__init__.py
rainbow/datasources/base.py
rainbow/datasources/cfn_datasource.py
rainbow/datasources/datasource_exceptions.py
rainbow/datasources/file_datasource.py
rainbow/datasources/yaml_datasource.py
rainbow/preprocessor/__init__.py
rainbow/preprocessor/base.py
rainbow/preprocessor/instance_chooser.py
rainbow/preprocessor/preprocessor_exceptions.py
rainbow_cfn.egg-info/PKG-INFO
rainbow_cfn.egg-info/SOURCES.txt
rainbow_cfn.egg-info/dependency_links.txt
rainbow_cfn.egg-info/entry_points.txt
rainbow_cfn.egg-info/requires.txt
rainbow_cfn.egg-info/top_level.txt
tests/__init__.py
tests/test_cfn_datasource.py
tests/test_cfn_deep_merge.py
tests/test_cloudformation.py
tests/test_datasources.py
tests/test_preprocessor.py
tests/test_yamlfile.py