Metadata-Version: 1.1
Name: rainbow-cfn
Version: 0.4
Summary: Rainbow is AWS Cloudformation on steroids
Home-page: http://github.com/EverythingMe/rainbow
Author: EverythingMe
Author-email: omrib@everything.me
License: UNKNOWN
Platform: UNKNOWN
Classifier: Development Status :: 5 - Production/Stable
Classifier: Environment :: Console
Classifier: Intended Audience :: Developers
Classifier: Intended Audience :: System Administrators
Classifier: Operating System :: OS Independent
Classifier: Programming Language :: Python :: 2.7
Classifier: Topic :: System :: Clustering
Classifier: Topic :: System :: Systems Administration
Classifier: Topic :: Utilities
